A_FMM/__init__.py
A_FMM/_version.py
A_FMM/creator.py
A_FMM/inputs.py
A_FMM/layer.py
A_FMM/scattering.py
A_FMM/stack.py
A_FMM/sub_sm.py
a_fmm-0.1.2.dist-info/METADATA
a_fmm-0.1.2.dist-info/WHEEL
a_fmm-0.1.2.dist-info/licenses/LICENSE
a_fmm-0.1.2.dist-info/RECORD
