Metadata-Version: 2.1
Name: A_FMM
Version: 0.1.2
Summary: Python implementation of the Aperiodic-Fourier Modal Method for electromagnetic simulation
Author-email: Marco Passoni <mpasson91@gmail.com>
License: MIT
License-File: LICENSE
Keywords: fourier modal methods,photonics,scattering matrix,simulation
Classifier: Development Status :: 4 - Beta
Classifier: Environment :: Console
Classifier: Intended Audience :: Developers
Classifier: Intended Audience :: Education
Classifier: Intended Audience :: Science/Research
Classifier: License :: OSI Approved :: MIT License
Classifier: Operating System :: OS Independent
Classifier: Programming Language :: Python
Classifier: Programming Language :: Python :: 3 :: Only
Classifier: Programming Language :: Python :: 3.11
Classifier: Programming Language :: Python :: 3.12
Classifier: Topic :: Scientific/Engineering :: Physics
Requires-Python: >=3.10
Requires-Dist: matplotlib>=3.5.1
Requires-Dist: numpy>=1.23.1
Requires-Dist: pandas>=1.4.2
Requires-Dist: scipy>=1.8.0
Provides-Extra: dev
Requires-Dist: hatch-vcs==0.3.0; extra == 'dev'
Requires-Dist: pytest>=7.2.0; extra == 'dev'
Requires-Dist: toml>=0.10.2; extra == 'dev'
Provides-Extra: doc
Requires-Dist: nbsphinx>=0.8.12; extra == 'doc'
Requires-Dist: notebook>=6.5.2; extra == 'doc'
Requires-Dist: sphinx-rtd-theme>=1.1.1; extra == 'doc'
Requires-Dist: sphinx>=5.3.0; extra == 'doc'
